ttsdm_pkg/__init__.py
ttsdm_pkg/__main__.py
ttsdm_pkg/Model/Card.py
ttsdm_pkg/Model/Deck.py
ttsdm_pkg/Model/ImageSheet.py
ttsdm_pkg/Model/ObjectStates.py
ttsdm_pkg/Model/__init__.py
ttsdm_pkg/Utils/Cards.py
ttsdm_pkg/Utils/ImageSheetManager.py
ttsdm_pkg/Utils/Imgur.py
ttsdm_pkg/Utils/Scrython.py
ttsdm_pkg/Utils/Url.py
ttsdm_pkg/Utils/__init__.py
ttsDeckMaker_pkg_Biduleman-0.0.6.dist-info/LICENSE
ttsDeckMaker_pkg_Biduleman-0.0.6.dist-info/METADATA
ttsDeckMaker_pkg_Biduleman-0.0.6.dist-info/WHEEL
ttsDeckMaker_pkg_Biduleman-0.0.6.dist-info/top_level.txt
ttsDeckMaker_pkg_Biduleman-0.0.6.dist-info/RECORD
