Metadata-Version: 2.1
Name: ttsDeckMaker-pkg-Biduleman
Version: 0.0.6
Summary: MTG Deck Maker for Tabletop Simulator.
Home-page: UNKNOWN
Author: Biduleman
Author-email: biduleman@gmail.com
License: UNKNOWN
Platform: UNKNOWN
Classifier: Programming Language :: Python :: 3
Classifier: License :: OSI Approved :: MIT License
Classifier: Operating System :: OS Independent
Requires-Python: >=3.6
Requires-Dist: Pillow
Requires-Dist: scrython
Requires-Dist: urllib3
Requires-Dist: requests
